bench_ai/__init__.py
bench_ai/cli.py
bench_ai-0.0.1.dist-info/licenses/LICENSE
bench_ai-0.0.1.dist-info/METADATA
bench_ai-0.0.1.dist-info/WHEEL
bench_ai-0.0.1.dist-info/entry_points.txt
bench_ai-0.0.1.dist-info/top_level.txt
bench_ai-0.0.1.dist-info/RECORD
